LICENSE.rst
MANIFEST.in
README.rst
confiskus.py
setup.py
confiskus.egg-info/PKG-INFO
confiskus.egg-info/SOURCES.txt
confiskus.egg-info/dependency_links.txt
confiskus.egg-info/top_level.txt