Metadata-Version: 1.1
Name: confiskus
Version: 1.0.6
Summary: INI style files parser with basic inheritance feature.
Home-page: https://github.com/beezz/confiskus
Author: Michal Kuffa
Author-email: michal.kuffa@gmail.com
License: BSD
Platform: UNKNOWN
Classifier: Intended Audience :: Developers
Classifier: License :: OSI Approved :: BSD License
Classifier: Operating System :: OS Independent
Classifier: Topic :: Software Development
Classifier: Programming Language :: Python :: 2.6
Classifier: Programming Language :: Python :: 2.7
